pandas_eda/__init__.py
pandas_eda/explore.py
pandas_eda/streamlit_app.py
pandas_eda/_testing/__init__.py
pandas_eda-1.2.0.dist-info/LICENSE
pandas_eda-1.2.0.dist-info/METADATA
pandas_eda-1.2.0.dist-info/WHEEL
pandas_eda-1.2.0.dist-info/top_level.txt
pandas_eda-1.2.0.dist-info/RECORD
