Metadata-Version: 2.1
Name: pandas-eda
Version: 1.2.0
Summary: Exploratory Data Analysis app to display table and frequent values for each column
Home-page: https://github.com/lisrael1/pandas_eda
Author: Lior Israeli
Author-email: israelilior@gmail.com
Project-URL: Bug Tracker, https://github.com/lisrael1/pandas_eda/issues
Classifier: Programming Language :: Python :: 3
Classifier: License :: OSI Approved :: MIT License
Classifier: Operating System :: OS Independent
Requires-Python: >=3.6
License-File: LICENSE
Requires-Dist: scipy
Requires-Dist: tqdm
Requires-Dist: pandas (>1.5)
Requires-Dist: streamlit (>=1.13)
Requires-Dist: openpyxl
Requires-Dist: numpy
Requires-Dist: faker
Requires-Dist: codetiming
Requires-Dist: plotly
Requires-Dist: pytest
